pyroughtime/__init__.py
pyroughtime/__version__.py
pyroughtime/pyroughtime.py
pyroughtime-1.0.1.dist-info/LICENSE
pyroughtime-1.0.1.dist-info/METADATA
pyroughtime-1.0.1.dist-info/WHEEL
pyroughtime-1.0.1.dist-info/top_level.txt
pyroughtime-1.0.1.dist-info/RECORD
