Metadata-Version: 2.1
Name: pyroughtime
Version: 1.0.1
Summary: pyroughtime - A Python 3 Roughtime implementation
Author-email: Aaron Meese <aaron@meese.enterprises>
License: GNU GENERAL PUBLIC LICENSE
Project-URL: Repository, https://github.com/meese-enterprises/pyroughtime
Project-URL: Issues, https://github.com/meese-enterprises/pyroughtime/issues
Keywords: roughtime,time,timestamp,security,cryptography
Classifier: Development Status :: 4 - Beta
Classifier: Intended Audience :: Developers
Classifier: Programming Language :: Python :: 3.7
Requires-Python: <3.12,>=3.7
License-File: LICENSE
Requires-Dist: ed25519
Requires-Dist: pycrypto
